httpbl.py
httpbl-1.0.1.dist-info/METADATA
httpbl-1.0.1.dist-info/RECORD
httpbl-1.0.1.dist-info/WHEEL
httpbl-1.0.1.dist-info/top_level.txt
httpbl-1.0.1.dist-info/zip-safe
